Beautifly_B/BrushingDataframe-Development.py
Beautifly_B/BrushingDataframe.py
Beautifly_B/__init__.py
Beautifly_B/demo.py
Beautifly_B/ordinal.py
Beautifly_B/print_msg.py
Beautifly_B/stats_bs.py
Beautifly_B/woe.py
Beautifly_B-0.1.6.1.dist-info/METADATA
Beautifly_B-0.1.6.1.dist-info/WHEEL
Beautifly_B-0.1.6.1.dist-info/top_level.txt
Beautifly_B-0.1.6.1.dist-info/RECORD
